package_name_again/__init__.py
package_name_again/my_stats.py
package_name_again-0.4.0.dist-info/WHEEL
package_name_again-0.4.0.dist-info/entry_points.txt
package_name_again-0.4.0.dist-info/METADATA
package_name_again-0.4.0.dist-info/RECORD
