Metadata-Version: 2.3
Name: package-name-again
Version: 0.4.0
Summary: Add your description here
Author: jacobdstates2020
Author-email: jacobdstates2020 <jacobdstates2020@gmail.com>
Requires-Dist: scipy>=1.15.3
Requires-Python: >=3.10
